CHANGES.txt
LICENSE
MANIFEST.in
README.md
setup.py
sanic_zipkin/__init__.py
sanic_zipkin/sanic_zipkin.py
sanic_zipkin.egg-info/PKG-INFO
sanic_zipkin.egg-info/SOURCES.txt
sanic_zipkin.egg-info/dependency_links.txt
sanic_zipkin.egg-info/requires.txt
sanic_zipkin.egg-info/top_level.txt
sanic_zipkin.egg-info/zip-safe