Metadata-Version: 1.1
Name: sanic-zipkin
Version: 0.1.2
Summary: Sanic plugin to use Distributed tracing instrumentation for asyncio application with aiozipkin
Home-page: https://github.com/kevinqqnj/sanic-zipkin
Author: Kevin ZHANG Qing
Author-email: ezhqing@gmail.com
License: LICENSE.txt
Download-URL: https://pypi.python.org/pypi/sanic-zipkin
Keywords: sanic,sanic plugin,zipkin,distributed-tracing,tracing
Platform: POSIX
Classifier: License :: OSI Approved :: MIT License
Classifier: Intended Audience :: Developers
Classifier: Programming Language :: Python :: 3
Classifier: Programming Language :: Python :: 3.5
Classifier: Programming Language :: Python :: 3.6
Classifier: Operating System :: POSIX
